{
	"configurations" : 
	[
		{
			"directories" : 
			[
				{
					"build" : ".",
					"hasInstallRule" : true,
					"jsonFile" : "directory-.-b56bb729ceb9c2c88e76.json",
					"minimumCMakeVersion" : 
					{
						"string" : "3.15"
					},
					"projectIndex" : 0,
					"source" : ".",
					"targetIndexes" : 
					[
						0,
						1,
						2,
						3,
						4,
						5
					]
				}
			],
			"name" : "",
			"projects" : 
			[
				{
					"directoryIndexes" : 
					[
						0
					],
					"name" : "examples_rclcpp_minimal_composition",
					"targetIndexes" : 
					[
						0,
						1,
						2,
						3,
						4,
						5
					]
				}
			],
			"targets" : 
			[
				{
					"directoryIndex" : 0,
					"id" : "composition_composed::@6890427a1f51a3e7e1df",
					"jsonFile" : "target-composition_composed-ffe945fbe7e02551e187.json",
					"name" : "composition_composed",
					"projectIndex" : 0
				},
				{
					"directoryIndex" : 0,
					"id" : "composition_nodes::@6890427a1f51a3e7e1df",
					"jsonFile" : "target-composition_nodes-4180ac732d1ded0079ae.json",
					"name" : "composition_nodes",
					"projectIndex" : 0
				},
				{
					"directoryIndex" : 0,
					"id" : "composition_publisher::@6890427a1f51a3e7e1df",
					"jsonFile" : "target-composition_publisher-cf7c4a8c183d303283d2.json",
					"name" : "composition_publisher",
					"projectIndex" : 0
				},
				{
					"directoryIndex" : 0,
					"id" : "composition_subscriber::@6890427a1f51a3e7e1df",
					"jsonFile" : "target-composition_subscriber-39ded40d43150bd6a76a.json",
					"name" : "composition_subscriber",
					"projectIndex" : 0
				},
				{
					"directoryIndex" : 0,
					"id" : "examples_rclcpp_minimal_composition_uninstall::@6890427a1f51a3e7e1df",
					"jsonFile" : "target-examples_rclcpp_minimal_composition_uninstall-f32bb2e6fb112492b3fd.json",
					"name" : "examples_rclcpp_minimal_composition_uninstall",
					"projectIndex" : 0
				},
				{
					"directoryIndex" : 0,
					"id" : "uninstall::@6890427a1f51a3e7e1df",
					"jsonFile" : "target-uninstall-efcfa060c54b5a7978b8.json",
					"name" : "uninstall",
					"projectIndex" : 0
				}
			]
		}
	],
	"kind" : "codemodel",
	"paths" : 
	{
		"build" : "/home/nazerke/ros2_ws/build/examples_rclcpp_minimal_composition",
		"source" : "/home/nazerke/ros2_ws/src/examples/rclcpp/composition/minimal_composition"
	},
	"version" : 
	{
		"major" : 2,
		"minor" : 6
	}
}
